aemo_nmi_info/__init__.py
aemo_nmi_info/nmi_lookup.py
aemo_nmi_info-0.0.2.dist-info/LICENSE
aemo_nmi_info-0.0.2.dist-info/METADATA
aemo_nmi_info-0.0.2.dist-info/WHEEL
aemo_nmi_info-0.0.2.dist-info/top_level.txt
aemo_nmi_info-0.0.2.dist-info/RECORD
