Metadata-Version: 2.1
Name: aemo_nmi_info
Version: 0.0.2
Summary: A package to look up AEMO NMI information
Home-page: https://github.com/powston/aemo_nmi_info
Author: Ian Connor
Author-email: ian@powston.com
License: UNKNOWN
Platform: UNKNOWN
Classifier: Development Status :: 3 - Alpha
Classifier: Intended Audience :: Developers
Classifier: License :: OSI Approved :: MIT License
Classifier: Operating System :: OS Independent
Classifier: Programming Language :: Python :: 3
Classifier: Programming Language :: Python :: 3.6
Classifier: Programming Language :: Python :: 3.7
Classifier: Programming Language :: Python :: 3.8
Classifier: Programming Language :: Python :: 3.9
Requires-Python: >=3.6
License-File: LICENSE
